{
  "annotations": {
    "changelogDate": "20240613173829"
  },
  "applications": "*",
  "dto": "mapstruct",
  "fields": [
    {
      "fieldName": "remitenteId",
      "fieldType": "Long",
      "fieldValidateRules": ["required"]
    },
    {
      "fieldName": "destinatarioId",
      "fieldType": "Long",
      "fieldValidateRules": ["required"]
    },
    {
      "fieldName": "mensaje",
      "fieldType": "String",
      "fieldValidateRules": ["required"]
    },
    {
      "fieldName": "leido",
      "fieldType": "Boolean"
    }
  ],
  "name": "Mensaje",
  "pagination": "pagination",
  "relationships": [],
  "searchEngine": "no",
  "service": "serviceClass"
}
